aiongrok/__init__.py
aiongrok-0.0.1.dist-info/DESCRIPTION.rst
aiongrok-0.0.1.dist-info/METADATA
aiongrok-0.0.1.dist-info/RECORD
aiongrok-0.0.1.dist-info/WHEEL
aiongrok-0.0.1.dist-info/metadata.json
aiongrok-0.0.1.dist-info/top_level.txt
