Metadata-Version: 2.0
Name: aiongrok
Version: 0.0.1
Summary: aiohttp ngrok API library
Home-page: https://github.com/resurtm/aiongrok
Author: resurtm
Author-email: resurtm@gmail.com
License: MIT
Download-URL: https://github.com/resurtm/aiongrok/archive/v0.0.1.tar.gz
Platform: any
Classifier: Development Status :: 2 - Pre-Alpha
Classifier: Intended Audience :: Developers
Classifier: License :: OSI Approved :: MIT License
Classifier: Operating System :: OS Independent
Classifier: Programming Language :: Python
Classifier: Programming Language :: Python :: 3
Classifier: Programming Language :: Python :: 3.5
Classifier: Programming Language :: Python :: 3.6
Classifier: Programming Language :: Python :: Implementation :: CPython
Classifier: Programming Language :: Python :: Implementation :: PyPy
Classifier: Topic :: Software Development :: Libraries :: Python Modules
Requires-Dist: aiohttp
